eventyst/__init__.py
eventyst/__main__.py
eventyst/_enums.py
eventyst/_exceptions.py
eventyst/adapters/__init__.py
eventyst/adapters/aws/__init__.py
eventyst/adapters/aws/schema_registry.py
eventyst/adapters/kafka.py
eventyst/cli/__init__.py
eventyst/cli/main.py
eventyst/cli/styles.py
eventyst/cli/utilities.py
eventyst/configuration.py
eventyst/core/__init__.py
eventyst/core/application.py
eventyst/core/commands.py
eventyst/core/dependency.py
eventyst/core/events.py
eventyst/core/handler_registry.py
eventyst/core/message_bus.py
eventyst/schema.py
eventyst/serialization/__init__.py
eventyst/serialization/codec.py
eventyst/serialization/naming.py
eventyst/serialization/registry.py
eventyst/serialization/serializers.py
eventyst/utilities/__init__.py
eventyst/utilities/async_tools.py
eventyst/utilities/avro_schema.py
eventyst/utilities/function_inspection.py
eventyst/utilities/log.py
eventyst/utilities/plotting.py
eventyst-0.1.2.dist-info/LICENSE
eventyst-0.1.2.dist-info/METADATA
eventyst-0.1.2.dist-info/WHEEL
eventyst-0.1.2.dist-info/entry_points.txt
eventyst-0.1.2.dist-info/RECORD
